<?xml version="1.0" encoding="UTF-8"?>
<workspaceFilter version="1.0">
    <filter root="/conf/my-aem-site" mode="merge"/>
    <filter root="/content/my-aem-site" mode="merge"/>
    <filter root="/content/dam/my-aem-site" mode="merge">
        <exclude pattern="/content/dam/my-aem-site(/.*)?"/>
        <include pattern="/content/dam/my-aem-site/jcr:content(/.*)?"/>
    </filter>
    <filter root="/content/dam/my-aem-site/asset.jpg" mode="merge"/>
    <filter root="/content/experience-fragments/my-aem-site" mode="merge"/>
</workspaceFilter>
